ccms/__init__.py
ccms/config.py
ccms/main.py
ccms/__pycache__/__init__.cpython-312.pyc
ccms/__pycache__/config.cpython-312.pyc
ccms/__pycache__/main.cpython-312.pyc
ccms/commands/__init__.py
ccms/commands/compliance_commands.py
ccms/commands/contract_commands.py
ccms/commands/__pycache__/__init__.cpython-312.pyc
ccms/commands/__pycache__/compliance_commands.cpython-312.pyc
ccms/commands/__pycache__/contract_commands.cpython-312.pyc
ccms/database/__init__.py
ccms/database/supabase_client.py
ccms/database/__pycache__/__init__.cpython-312.pyc
ccms/database/__pycache__/supabase_client.cpython-312.pyc
ccms/parsers/__init__.py
ccms/parsers/base.py
ccms/parsers/docx_parser.py
ccms/parsers/pdf_parser.py
ccms/parsers/__pycache__/__init__.cpython-312.pyc
ccms/parsers/__pycache__/base.cpython-312.pyc
ccms/parsers/__pycache__/docx_parser.cpython-312.pyc
ccms/parsers/__pycache__/pdf_parser.cpython-312.pyc
ccms/utils/__init__.py
ccms/utils/compliance_checker.py
ccms/utils/report_generator.py
ccms/utils/__pycache__/__init__.cpython-312.pyc
ccms/utils/__pycache__/compliance_checker.cpython-312.pyc
ccms/utils/__pycache__/report_generator.cpython-312.pyc
ccms-0.1.0.dist-info/LICENSE
ccms-0.1.0.dist-info/METADATA
ccms-0.1.0.dist-info/WHEEL
ccms-0.1.0.dist-info/top_level.txt
ccms-0.1.0.dist-info/RECORD
