Metadata-Version: 2.1
Name: ccms
Version: 0.1.0
Summary: A Contract and Compliance Management System using Python and Supabase
Home-page: https://github.com/VinVorteX/ccms
Author: Vinayak Rastogi
Author-email: Vinayak Rastogi <rvinayak108@gmail.com>
License: MIT License
Project-URL: Homepage, https://github.com/VinVorteX/ccms
Requires-Python: >=3.8
License-File: LICENSE
